zfit/__init__.py
zfit/__init__.pyi
zfit/_data/__init__.pyi
zfit/_data/binneddatav1.pyi
zfit/_data/unbinneddata.pyi
zfit/_interfaces.pyi
zfit/_loss/__init__.pyi
zfit/_loss/binnedloss.pyi
zfit/_variables/__init__.pyi
zfit/_variables/axis.pyi
zfit/_variables/varsupport.pyi
zfit/_version.pyi
zfit/binned.pyi
zfit/constraint.pyi
zfit/core/__init__.pyi
zfit/core/basefunc.pyi
zfit/core/basemodel.pyi
zfit/core/baseobject.pyi
zfit/core/basepdf.pyi
zfit/core/binnedpdf.pyi
zfit/core/binning.pyi
zfit/core/constraint.pyi
zfit/core/coordinates.pyi
zfit/core/data.pyi
zfit/core/dimension.pyi
zfit/core/func.pyi
zfit/core/integration.pyi
zfit/core/loss.pyi
zfit/core/operations.pyi
zfit/core/parameter.pyi
zfit/core/pdf.pyi
zfit/core/sample.pyi
zfit/core/serialmixin.pyi
zfit/core/space.pyi
zfit/core/tensorlike.pyi
zfit/core/values.pyi
zfit/data.pyi
zfit/dill.pyi
zfit/dimension.pyi
zfit/exception.pyi
zfit/func.pyi
zfit/hs3.pyi
zfit/interface.pyi
zfit/loss.pyi
zfit/minimize.pyi
zfit/minimizers/__init__.pyi
zfit/minimizers/base_tf.pyi
zfit/minimizers/baseminimizer.pyi
zfit/minimizers/errors.pyi
zfit/minimizers/evaluation.pyi
zfit/minimizers/fitresult.pyi
zfit/minimizers/interface.pyi
zfit/minimizers/ipopt.pyi
zfit/minimizers/minimizer_lm.pyi
zfit/minimizers/minimizer_minuit.pyi
zfit/minimizers/minimizer_nlopt.pyi
zfit/minimizers/minimizer_tfp.pyi
zfit/minimizers/minimizers_scipy.pyi
zfit/minimizers/optimizers_tf.pyi
zfit/minimizers/strategy.pyi
zfit/minimizers/termination.pyi
zfit/models/__init__.pyi
zfit/models/basefunctor.pyi
zfit/models/basic.pyi
zfit/models/binned_functor.pyi
zfit/models/cache.pyi
zfit/models/conditional.pyi
zfit/models/convolution.pyi
zfit/models/dist_tfp.pyi
zfit/models/functions.pyi
zfit/models/functor.pyi
zfit/models/histmodifier.pyi
zfit/models/histogram.pyi
zfit/models/interpolation.pyi
zfit/models/kde.pyi
zfit/models/morphing.pyi
zfit/models/physics.pyi
zfit/models/polynomials.pyi
zfit/models/postprocess.pyi
zfit/models/special.pyi
zfit/models/template.pyi
zfit_stubs-0.0.1.dev20.dist-info/METADATA
zfit_stubs-0.0.1.dev20.dist-info/WHEEL
zfit_stubs-0.0.1.dev20.dist-info/RECORD
